campi/__init__.py
campi/client/__init__.py
campi/client/qtclient.py
campi/server/__init__.py
campi/server/camserver.py
campi/server/movie-server.py
campi-0.1.2.dist-info/DESCRIPTION.rst
campi-0.1.2.dist-info/METADATA
campi-0.1.2.dist-info/RECORD
campi-0.1.2.dist-info/WHEEL
campi-0.1.2.dist-info/entry_points.txt
campi-0.1.2.dist-info/metadata.json
campi-0.1.2.dist-info/top_level.txt
