Metadata-Version: 2.0
Name: campi
Version: 0.1.2
Summary: Camera server and client software for Raspberry Pi beam profiling camera
Home-page: https://gitlab.physik.uni-muenchen.de/luis.riegger/campi
Author: lsrggr
Author-email: lri@me.com
License: MIT
Keywords: physics cold atoms experiment control
Platform: UNKNOWN
Classifier: Development Status :: 4 - Beta
Classifier: Programming Language :: Python :: 3.6
Requires-Dist: pyqt5
Requires-Dist: numpy
Requires-Dist: scipy
Requires-Dist: pyqtgraph
Requires-Dist: pillow
Requires-Dist: scikit-image
Requires-Dist: setuptools-scm
